wordfence/__init__.py
wordfence/version.py
wordfence/api/__init__.py
wordfence/api/exceptions.py
wordfence/api/intelligence.py
wordfence/api/licensing.py
wordfence/api/noc1.py
wordfence/api/noc4.py
wordfence/api/noc_client.py
wordfence/cli/__init__.py
wordfence/cli/auto_complete.py
wordfence/cli/cli.py
wordfence/cli/configurer.py
wordfence/cli/context.py
wordfence/cli/email.py
wordfence/cli/exceptions.py
wordfence/cli/helper.py
wordfence/cli/io.py
wordfence/cli/licensing.py
wordfence/cli/mailing_lists.py
wordfence/cli/reporting.py
wordfence/cli/subcommands.py
wordfence/cli/terms_management.py
wordfence/cli/test_malwarescan_filter.py
wordfence/cli/banner/__init__.py
wordfence/cli/banner/banner.py
wordfence/cli/config/__init__.py
wordfence/cli/config/base_config_definitions.py
wordfence/cli/config/cli_parser.py
wordfence/cli/config/config.py
wordfence/cli/config/config_items.py
wordfence/cli/config/defaults.py
wordfence/cli/config/ini_parser.py
wordfence/cli/config/typing.py
wordfence/cli/configure/configure.py
wordfence/cli/configure/definition.py
wordfence/cli/countsites/countsites.py
wordfence/cli/countsites/definition.py
wordfence/cli/dbscan/dbscan.py
wordfence/cli/dbscan/definition.py
wordfence/cli/dbscan/reporting.py
wordfence/cli/help/definition.py
wordfence/cli/help/help.py
wordfence/cli/malwarescan/__init__.py
wordfence/cli/malwarescan/definition.py
wordfence/cli/malwarescan/malwarescan.py
wordfence/cli/malwarescan/progress.py
wordfence/cli/malwarescan/reporting.py
wordfence/cli/remediate/definition.py
wordfence/cli/remediate/remediate.py
wordfence/cli/remediate/reporting.py
wordfence/cli/terms/definition.py
wordfence/cli/terms/terms.py
wordfence/cli/version/definition.py
wordfence/cli/version/version.py
wordfence/cli/vulnscan/definition.py
wordfence/cli/vulnscan/exceptions.py
wordfence/cli/vulnscan/reporting.py
wordfence/cli/vulnscan/vulnscan.py
wordfence/databasescanning/__init__.py
wordfence/databasescanning/scanner.py
wordfence/intel/__init__.py
wordfence-5.0.2.dist-info/LICENSE
wordfence-5.0.2.dist-info/METADATA
wordfence-5.0.2.dist-info/WHEEL
wordfence-5.0.2.dist-info/entry_points.txt
wordfence-5.0.2.dist-info/top_level.txt
wordfence-5.0.2.dist-info/RECORD
