Metadata-Version: 2.1
Name: wordfence
Version: 5.0.2
Summary: Command-line malware scanner powered by Wordfence
Author-email: Wordfence <opensource@wordfence.com>
Maintainer-email: Wordfence <opensource@wordfence.com>
License: GNU GENERAL PUBLIC LICENSE
Project-URL: Homepage, https://www.wordfence.com/products/wordfence-cli/
Project-URL: Documentation, https://www.wordfence.com/help/wordfence-cli/
Project-URL: Repository, https://github.com/wordfence/wordfence-cli
Classifier: Programming Language :: Python :: 3
Classifier: License :: OSI Approved :: GNU General Public License v3 (GPLv3)
Classifier: Operating System :: OS Independent
Classifier: Environment :: Console
Classifier: Intended Audience :: Information Technology
Classifier: Intended Audience :: System Administrators
Classifier: Topic :: Security
Requires-Python: >=3.8
License-File: LICENSE
Requires-Dist: packaging >=21.0
Requires-Dist: requests >=2.3
Requires-Dist: pymysql >=0.9.3
